eldartools/__init__.py
eldartools/date_utils.py
eldartools/dict_utils.py
eldartools/file_utils.py
eldartools/list_utils.py
eldartools/number_utils.py
eldartools/security_utils.py
eldartools/string_utils.py
eldartools-0.2.0.dist-info/METADATA
eldartools-0.2.0.dist-info/WHEEL
eldartools-0.2.0.dist-info/top_level.txt
eldartools-0.2.0.dist-info/RECORD
