Metadata-Version: 2.4
Name: eldartools
Version: 0.2.0
Summary: All-in-one Python utilities: strings, lists, dicts, numbers, files, dates, security.
Author: Eldar Eliyev
Author-email: eldar@example.com
Requires-Python: >=3.7
Dynamic: author
Dynamic: author-email
Dynamic: description
Dynamic: description-content-type
Dynamic: requires-python
Dynamic: summary
